fileblock/Abstrcat.py
fileblock/Block.py
fileblock/Directory.py
fileblock/__init__.py
fileblock/__version__.py
fileblock/btype.py
fileblock/utils.py
fileblock-2.0.3.2022.6.27.dist-info/LICENSE
fileblock-2.0.3.2022.6.27.dist-info/METADATA
fileblock-2.0.3.2022.6.27.dist-info/WHEEL
fileblock-2.0.3.2022.6.27.dist-info/top_level.txt
fileblock-2.0.3.2022.6.27.dist-info/RECORD
