Metadata-Version: 2.1
Name: fileblock
Version: 2.0.3.2022.6.27
Summary: simplify file processing
Home-page: http://github.com/miaobuao/fileblock
Author: miaobuao
Author-email: 617802189@qq.com
License: Apache 2.0
Platform: UNKNOWN
Classifier: Programming Language :: Python :: 3
Classifier: License :: OSI Approved :: Apache Software License
Classifier: Operating System :: OS Independent
License-File: LICENSE
